src_4x4/fixedpoint.sv
//--------------------------------------------------------------------------------------------------------
// Module  : fxp_zoom
// Type    : synthesizable
// Standard: Verilog 2001 (IEEE1364-2001)
// Function: bit width conversion for fixed-point
//           combinational logic
//--------------------------------------------------------------------------------------------------------

module fxp_zoom #(
    parameter WII  = 8,
    parameter WIF  = 8,
    parameter WOI  = 8,
    parameter WOF  = 8,
    parameter ROUND= 1
)(
    input  wire [WII+WIF-1:0] in,
    output wire [WOI+WOF-1:0] out,
    output reg                overflow
);

initial overflow = 1'b0;

reg [WII+WOF-1:0] inr = 0;
reg [WII-1:0] ini = 0;
reg [WOI-1:0] outi = 0;
reg [WOF-1:0] outf = 0;

generate if(WOF<WIF) begin
    if(ROUND==0) begin
        always @ (*) inr = in[WII+WIF-1:WIF-WOF];
    end else if(WII+WOF>=2) begin
        always @ (*) begin
            inr = in[WII+WIF-1:WIF-WOF];
            if(in[WIF-WOF-1] & ~(~inr[WII+WOF-1] & (&inr[WII+WOF-2:0]))) inr=inr+1;
        end
    end else begin
        always @ (*) begin
            inr = in[WII+WIF-1:WIF-WOF];
            if(in[WIF-WOF-1] & inr[WII+WOF-1]) inr=inr+1;
        end
    end
end else if(WOF==WIF) begin
    always @ (*) inr[WII+WOF-1:WOF-WIF] = in;
end else begin
    always @ (*) begin
        inr[WII+WOF-1:WOF-WIF] = in;
        inr[WOF-WIF-1:0] = 0;
    end
end endgenerate


generate if(WOI<WII) begin
    always @ (*) begin
        {ini, outf} = inr;
        if         ( ~ini[WII-1] & |ini[WII-2:WOI-1] ) begin
            overflow = 1'b1;
            outi = {WOI{1'b1}};
            outi[WOI-1] = 1'b0;
            outf = {WOF{1'b1}};
        end else if(  ini[WII-1] & ~(&ini[WII-2:WOI-1]) ) begin
            overflow = 1'b1;
            outi = 0;
            outi[WOI-1] = 1'b1;
            outf = 0;
        end else begin
            overflow = 1'b0;
            outi = ini[WOI-1:0];
        end
    end
end else begin
    always @ (*) begin
        {ini, outf} = inr;
        overflow = 1'b0;
        outi = ini[WII-1] ? {WOI{1'b1}} : 0;
        outi[WII-1:0] = ini;
    end
end endgenerate

assign out = {outi, outf};

endmodule







//--------------------------------------------------------------------------------------------------------
// Module  : fxp_add
// Type    : synthesizable
// Standard: Verilog 2001 (IEEE1364-2001)
// Function: addition
//           combinational logic
//--------------------------------------------------------------------------------------------------------

module fxp_add # (
    parameter WIIA = 8,
    parameter WIFA = 8,
    parameter WIIB = 8,
    parameter WIFB = 8,
    parameter WOI  = 8,
    parameter WOF  = 8,
    parameter ROUND= 1
)(
    input  wire [WIIA+WIFA-1:0] ina,
    input  wire [WIIB+WIFB-1:0] inb,
    output wire [WOI +WOF -1:0] out,
    output wire                 overflow
);

localparam WII = WIIA>WIIB ? WIIA : WIIB;
localparam WIF = WIFA>WIFB ? WIFA : WIFB;
localparam WRI = WII + 1;
localparam WRF = WIF;

wire [WII+WIF-1:0] inaz, inbz;

wire signed [WRI+WRF-1:0] res = $signed(inaz) + $signed(inbz);

fxp_zoom # (
    .WII      ( WIIA     ),
    .WIF      ( WIFA     ),
    .WOI      ( WII      ),
    .WOF      ( WIF      ),
    .ROUND    ( 0        )
) ina_zoom (
    .in       ( ina      ),
    .out      ( inaz     ),
    .overflow (          )
);

fxp_zoom # (
    .WII      ( WIIB     ),
    .WIF      ( WIFB     ),
    .WOI      ( WII      ),
    .WOF      ( WIF      ),
    .ROUND    ( 0        )
) inb_zoom (
    .in       ( inb      ),
    .out      ( inbz     ),
    .overflow (          )
);

fxp_zoom # (
    .WII      ( WRI            ),
    .WIF      ( WRF            ),
    .WOI      ( WOI            ),
    .WOF      ( WOF            ),
    .ROUND    ( ROUND          )
) res_zoom (
    .in       ( $unsigned(res) ),
    .out      ( out            ),
    .overflow ( overflow       )
);

endmodule


//--------------------------------------------------------------------------------------------------------
// Module  : fxp_mul
// Type    : synthesizable
// Standard: Verilog 2001 (IEEE1364-2001)
// Function: multiplication
//           combinational logic
//--------------------------------------------------------------------------------------------------------

module fxp_mul # (
    parameter WIIA = 8,
    parameter WIFA = 8,
    parameter WIIB = 8,
    parameter WIFB = 8,
    parameter WOI  = 8,
    parameter WOF  = 8,
    parameter ROUND= 1
)(
    input  wire [WIIA+WIFA-1:0] ina,
    input  wire [WIIB+WIFB-1:0] inb,
    output wire [WOI +WOF -1:0] out,
    output wire                 overflow
);

localparam WRI = WIIA + WIIB;
localparam WRF = WIFA + WIFB;

wire signed [WRI+WRF-1:0] res = $signed(ina) * $signed(inb);

fxp_zoom # (
    .WII      ( WRI            ),
    .WIF      ( WRF            ),
    .WOI      ( WOI            ),
    .WOF      ( WOF            ),
    .ROUND    ( ROUND          )
) res_zoom (
    .in       ( $unsigned(res) ),
    .out      ( out            ),
    .overflow ( overflow       )
);

endmodule

//--------------------------------------------------------------------------------------------------------
// Module  : fxp_addsub
// Type    : synthesizable
// Standard: Verilog 2001 (IEEE1364-2001)
// Function: addition and subtraction
//           combinational logic
//--------------------------------------------------------------------------------------------------------

module fxp_addsub # (
    parameter WIIA = 8,
    parameter WIFA = 8,
    parameter WIIB = 8,
    parameter WIFB = 8,
    parameter WOI  = 8,
    parameter WOF  = 8,
    parameter ROUND= 1
)(
    input  wire [WIIA+WIFA-1:0] ina,
    input  wire [WIIB+WIFB-1:0] inb,
    input  wire                 sub, // 0=add, 1=sub
    output wire [WOI +WOF -1:0] out,
    output wire                 overflow
);

localparam WIIBE = WIIB + 1;
localparam   WII = WIIA>WIIBE ? WIIA : WIIBE;
localparam   WIF = WIFA>WIFB  ? WIFA : WIFB;
localparam   WRI = WII + 1;
localparam   WRF = WIF;

localparam [WIIBE+WIFB-1:0] ONE = 1;
wire [WIIBE+WIFB-1:0] inbe;
wire [   WII+WIF-1:0] inaz, inbz;
wire [WIIBE+WIFB-1:0] inbv = sub ? (~inbe)+ONE : inbe;
wire signed [WRI+WRF-1:0] res = $signed(inaz) + $signed(inbz);

fxp_zoom # (
    .WII      ( WIIB     ),
    .WIF      ( WIFB     ),
    .WOI      ( WIIBE    ),
    .WOF      ( WIFB     ),
    .ROUND    ( 0        )
) inb_extend (
    .in       ( inb      ),
    .out      ( inbe     ),
    .overflow (          )
);

fxp_zoom # (
    .WII      ( WIIA     ),
    .WIF      ( WIFA     ),
    .WOI      ( WII      ),
    .WOF      ( WIF      ),
    .ROUND    ( 0        )
) ina_zoom (
    .in       ( ina      ),
    .out      ( inaz     ),
    .overflow (          )
);

fxp_zoom # (
    .WII      ( WIIBE    ),
    .WIF      ( WIFB     ),
    .WOI      ( WII      ),
    .WOF      ( WIF      ),
    .ROUND    ( 0        )
) inb_zoom (
    .in       ( inbv     ),
    .out      ( inbz     ),
    .overflow (          )
);

fxp_zoom # (
    .WII      ( WRI            ),
    .WIF      ( WRF            ),
    .WOI      ( WOI            ),
    .WOF      ( WOF            ),
    .ROUND    ( ROUND          )
) res_zoom (
    .in       ( $unsigned(res) ),
    .out      ( out            ),
    .overflow ( overflow       )
);

endmodule

src/pe.sv
`timescale 1ns/1ps
`default_nettype none

module pe #(
    parameter int DATA_WIDTH = 16 //TODO: remove? we're not using this yet, lol)
) (
    input logic clk,
    input logic rst,

    // North wires of PE
    input logic signed [15:0] pe_psum_in, 
    input logic signed [15:0] pe_weight_in,
    input logic pe_accept_w_in, 
    
    // West wires of PE
    input logic signed [15:0] pe_input_in, 
    input logic pe_valid_in, 
    input logic pe_switch_in, 
    input logic pe_enabled,

    // South wires of the PE
    output logic signed [15:0] pe_psum_out,
    output logic signed [15:0] pe_weight_out,

    // East wires of the PE
    output logic signed [15:0] pe_input_out,
    output logic pe_valid_out,
    output logic pe_switch_out
);

    logic signed [15:0] mult_out;
    wire signed [15:0] mac_out; // just a wire
    logic signed [15:0] weight_reg_active; // foreground register
    logic signed[15:0] weight_reg_inactive; // background register

    fxp_mul mult (
        .ina(pe_input_in),
        .inb(weight_reg_active),
        .out(mult_out),
        .overflow()
    );

    fxp_add adder (
        .ina(mult_out),
        .inb(pe_psum_in),
        .out(mac_out),
        .overflow()
    );

    // Only the switch flag is combinational (active register copies inactive register on the same clock cycle that switch flag is set)
    // That means inputs from the left side of the PE can load in on the same clock cycle that the switch flag is set
    //always_comb begin
    //    if (pe_switch_in) begin
    //        weight_reg_active = weight_reg_inactive;
    //    end
    //end


    always_ff @(posedge clk or posedge rst) begin
        if (rst || !pe_enabled) begin
            pe_input_out <= 16'b0;
            weight_reg_active <= 16'b0;
            weight_reg_inactive <= 16'b0;
            pe_valid_out <= 0;
            pe_weight_out <= 16'b0;
            pe_switch_out <= 0;
        end else begin
            pe_valid_out <= pe_valid_in;
            pe_switch_out <= pe_switch_in;
            
            // Weight register updates - only on clock edges
            if (pe_accept_w_in) begin
                weight_reg_inactive <= pe_weight_in;
                pe_weight_out <= pe_weight_in;
            end else begin
                pe_weight_out <= 0;
            end

            if (pe_switch_in) begin
                if (pe_accept_w_in) begin
                    weight_reg_active <= pe_weight_in;
                end else begin
                    weight_reg_active <= weight_reg_inactive; // Loads inactive from previous edge
                end
            end
        // else: weight_reg_active retains its value

            if (pe_valid_in) begin
                pe_input_out <= pe_input_in;
                pe_psum_out <= mac_out;
            end else begin
                pe_valid_out <= 0;
                pe_psum_out <= 16'b0;
            end

        end
    end

endmodule

waveforms/pe.vcd
$date
	Wed Oct  1 17:15:29 2025
$end
$version
	Icarus Verilog
$end
$timescale
	1ps
$end
$scope module pe $end
$var wire 1 ! clk $end
$var wire 1 " pe_accept_w_in $end
$var wire 1 # pe_enabled $end
$var wire 16 $ pe_input_in [15:0] $end
$var wire 16 % pe_psum_in [15:0] $end
$var wire 1 & pe_switch_in $end
$var wire 1 ' pe_valid_in $end
$var wire 16 ( pe_weight_in [15:0] $end
$var wire 1 ) rst $end
$var wire 16 * mult_out [15:0] $end
$var wire 16 + mac_out [15:0] $end
$var parameter 32 , DATA_WIDTH $end
$var reg 16 - pe_input_out [15:0] $end
$var reg 16 . pe_psum_out [15:0] $end
$var reg 1 / pe_switch_out $end
$var reg 1 0 pe_valid_out $end
$var reg 16 1 pe_weight_out [15:0] $end
$var reg 16 2 weight_reg_active [15:0] $end
$var reg 16 3 weight_reg_inactive [15:0] $end
$scope module adder $end
$var wire 16 4 inb [15:0] $end
$var wire 17 5 res [16:0] $end
$var wire 1 6 overflow $end
$var wire 16 7 out [15:0] $end
$var wire 16 8 inbz [15:0] $end
$var wire 16 9 inaz [15:0] $end
$var wire 16 : ina [15:0] $end
$var parameter 32 ; ROUND $end
$var parameter 32 < WIF $end
$var parameter 32 = WIFA $end
$var parameter 32 > WIFB $end
$var parameter 32 ? WII $end
$var parameter 32 @ WIIA $end
$var parameter 32 A WIIB $end
$var parameter 32 B WOF $end
$var parameter 32 C WOI $end
$var parameter 32 D WRF $end
$var parameter 33 E WRI $end
$scope module ina_zoom $end
$var wire 16 F out [15:0] $end
$var wire 16 G in [15:0] $end
$var parameter 32 H ROUND $end
$var parameter 32 I WIF $end
$var parameter 32 J WII $end
$var parameter 32 K WOF $end
$var parameter 32 L WOI $end
$var reg 8 M ini [7:0] $end
$var reg 16 N inr [15:0] $end
$var reg 8 O outf [7:0] $end
$var reg 8 P outi [7:0] $end
$var reg 1 Q overflow $end
$scope begin genblk1 $end
$upscope $end
$scope begin genblk2 $end
$upscope $end
$upscope $end
$scope module inb_zoom $end
$var wire 16 R in [15:0] $end
$var wire 16 S out [15:0] $end
$var parameter 32 T ROUND $end
$var parameter 32 U WIF $end
$var parameter 32 V WII $end
$var parameter 32 W WOF $end
$var parameter 32 X WOI $end
$var reg 8 Y ini [7:0] $end
$var reg 16 Z inr [15:0] $end
$var reg 8 [ outf [7:0] $end
$var reg 8 \ outi [7:0] $end
$var reg 1 ] overflow $end
$scope begin genblk1 $end
$upscope $end
$scope begin genblk2 $end
$upscope $end
$upscope $end
$scope module res_zoom $end
$var wire 17 ^ in [16:0] $end
$var wire 16 _ out [15:0] $end
$var parameter 32 ` ROUND $end
$var parameter 32 a WIF $end
$var parameter 33 b WII $end
$var parameter 32 c WOF $end
$var parameter 32 d WOI $end
$var reg 9 e ini [8:0] $end
$var reg 17 f inr [16:0] $end
$var reg 8 g outf [7:0] $end
$var reg 8 h outi [7:0] $end
$var reg 1 6 overflow $end
$scope begin genblk1 $end
$upscope $end
$scope begin genblk2 $end
$upscope $end
$upscope $end
$upscope $end
$scope module mult $end
$var wire 16 i ina [15:0] $end
$var wire 16 j inb [15:0] $end
$var wire 32 k res [31:0] $end
$var wire 1 l overflow $end
$var wire 16 m out [15:0] $end
$var parameter 32 n ROUND $end
$var parameter 32 o WIFA $end
$var parameter 32 p WIFB $end
$var parameter 32 q WIIA $end
$var parameter 32 r WIIB $end
$var parameter 32 s WOF $end
$var parameter 32 t WOI $end
$var parameter 33 u WRF $end
$var parameter 33 v WRI $end
$scope module res_zoom $end
$var wire 32 w in [31:0] $end
$var wire 16 x out [15:0] $end
$var parameter 32 y ROUND $end
$var parameter 33 z WIF $end
$var parameter 33 { WII $end
$var parameter 32 | WOF $end
$var parameter 32 } WOI $end
$var reg 16 ~ ini [15:0] $end
$var reg 24 !" inr [23:0] $end
$var reg 8 "" outf [7:0] $end
$var reg 8 #" outi [7:0] $end
$var reg 1 l overflow $end
$scope begin genblk1 $end
$scope begin genblk1 $end
$upscope $end
$upscope $end
$scope begin genblk2 $end
$upscope $end
$upscope $end
$upscope $end
$upscope $end
$enddefinitions $end
$comment Show the parameter values. $end
$dumpall
b1000 }
b1000 |
b10000 {
b10000 z
b1 y
b10000 v
b10000 u
b1000 t
b1000 s
b1000 r
b1000 q
b1000 p
b1000 o
b1 n
b1000 d
b1000 c
b1001 b
b1000 a
b1 `
b1000 X
b1000 W
b1000 V
b1000 U
b0 T
b1000 L
b1000 K
b1000 J
b1000 I
b0 H
b1001 E
b1000 D
b1000 C
b1000 B
b1000 A
b1000 @
b1000 ?
b1000 >
b1000 =
b1000 <
b1 ;
b10000 ,
$end
#0
$dumpvars
b0 #"
b0 ""
b0 !"
b0 ~
b0 x
b0 w
b0 m
0l
b0 k
b0 j
b0 i
b0 h
b0 g
b0 f
b0 e
b0 _
b0 ^
0]
b0 \
b0 [
b0 Z
b0 Y
b0 S
b0 R
0Q
b0 P
b0 O
b0 N
b0 M
b0 G
b0 F
b0 :
b0 9
b0 8
b0 7
06
b0 5
b0 4
b0 3
b0 2
b0 1
00
0/
bx .
b0 -
b0 +
b0 *
0)
b0 (
0'
z&
b0 %
b0 $
z#
0"
1!
$end
#5000
0!
#10000
b100010100000000 (
1"
b0 .
z/
1!
#15000
0!
#20000
b101000000000 (
b100010100000000 1
b100010100000000 3
1!
#25000
0!
#30000
b1010000000000 9
b1010000000000 F
b10100 P
b10100 M
b100011000000000 +
b100011000000000 7
b100011000000000 _
b1000110 h
b1000110 e
b1010000000000 N
b100011000000000 f
b1010000000000 *
b1010000000000 :
b1010000000000 G
b1010000000000 m
b1010000000000 x
b10100 #"
b10100 ~
b100011000000000 5
b100011000000000 ^
b11001000000000 8
b11001000000000 S
b110010 \
b110010 Y
b1010000000000 !"
b11001000000000 Z
b101000000000000000000 k
b101000000000000000000 w
b101000000000 2
b101000000000 j
b11001000000000 %
b11001000000000 4
b11001000000000 R
b1000000000 $
b1000000000 i
1'
1&
0"
b101000000000 1
b101000000000 3
1!
#35000
0!
#40000
b100011000000000 .
b1000000000 -
b0 1
1/
10
1!
#45000
0!
#50000
0'
1!
#55000
0!
#60000
0&
b0 .
00
1!
#65000
0!
#70000
0/
1!
